configsuite/__about__.py
configsuite/__init__.py
configsuite/_version.py
configsuite/config.py
configsuite/meta_keys.py
configsuite/schema.py
configsuite/transformer.py
configsuite/types.py
configsuite/validation_errors.py
configsuite/validator.py
configsuite/docs/__init__.py
configsuite/extension/__init__.py
configsuite/extension/ext.py
configsuite/extension/ext_nodes.py
configsuite/extension/_static/configsuite_ext.css
configsuite/extension/_static/configsuite_ext.js
configsuite-0.6.7.dist-info/LICENSE
configsuite-0.6.7.dist-info/METADATA
configsuite-0.6.7.dist-info/WHEEL
configsuite-0.6.7.dist-info/top_level.txt
configsuite-0.6.7.dist-info/RECORD
